{
    "name": "Land Rover",
    "models": [
      { "id": 1, "name": "Defender"},
      { "id": 2, "name": "Discovery"},
      { "id": 3, "name": "Discovery Sport"},
      { "id": 4, "name": "Freelander"},
      { "id": 5, "name": "Lr3"},
      { "id": 6, "name": "Lr4"},
      { "id": 7, "name": "Ranger Rover"},
      { "id": 8, "name": "Range Rover Evoque"},
      { "id": 9, "name": "Range Rover Sport"},
      { "id": 10, "name": "Ranger Rover Velar"},
      { "id": 11, "name": "Series"}
    ]
  }