[
    {
      "id": 1,
      "route":"gov-regulations",
      "title": "Government Policies/Road Regulations",
      "content": {
        "trafficLaws":"Hello",
        "regulations":"yes",
        "inspection":"Hello",
        "registration":"yes",
        "licensing":"Hello"
      }
    },
    {
      "id": 2,
      "route":"driving-techniques",
      "img": "image goes here",
      "title": "Driving Techniques and Safety Tips",
      "content": {
        "drivingTechniques":"True",
        "drivingRisks":"False",
        "adverseConditions":"True"
      }
    },
    {
      "id": 3,
      "route":"community-engagements",
      "img": "image goes here",
      "title": "Community and Engagement",
      "content": {
        "carCommunities":"We",
        "carShows":"You"
      }
    },
    {
      "id": 3,
      "route":"jumping-battery",
      "img": "image goes here",
      "title": "Jumping a Dead Car Battery",
      "content": {
        "causes":"",
        "procedure":"",
        "preventing":""
      }
    },
    {
      "id": 4,
      "route":"vehicle-technologies",
      "title": "Vehicle Technology and Innovations",
      "content": {
        "latestAdvancements":"",
        "ADAS":""
      }
    },
    {
      "id": 5,
      "route":"upgrades",
      "img": "image goes here",
      "title": "Vehicle Upgrades",
      "content": {
        "popularUpgrades":"",
        "reputableBrands":"",
        "modificationImpacts":""
      }
    },
    {
      "id": 6,
      "route":"lpg-conversion",
      "img": "image goes here",
      "title": "LPG Conversion",
      "content": {
        "what":"",
        "reasons":"",
        "companies":"",
        "how":"",
        "pros":"",
        "cons":"",
        "conclusion":""
      }
    },
    {
      "id": 7,
      "route":"electric-mobility",
      "img": "image goes here",
      "title": "Electric Mobility",
      "content": {
        "advancements":"",
        "budgetCars":"",
        "economics":"",
        "maintenance":"",
        "ecosystem":"",
        "conclusion":""
      }
    }
]
  